[{"ID":1,"CodigoPostal":"1070-161","Morada":"Rua José da Silva Pais","Localidade":"LISBOA","Freguesia":"Campolide","Concelho":"Lisboa","CodigoDistrito":11,"Distrito":"Lisboa","Latitude":"38.731658","Longitude":"-9.172087"},{"ID":2,"CodigoPostal":"1070-161","Morada":"Rua José da Silva Pais","Localidade":"LISBOA","Freguesia":"Campolide","Concelho":"Lisboa","CodigoDistrito":11,"Distrito":"Lisboa","Latitude":"38.731658","Longitude":"-9.172087"},{"ID":3,"CodigoPostal":"1070-161","Morada":"Rua José da Silva Pais","Localidade":"LISBOA","Freguesia":"Campolide","Concelho":"Lisboa","CodigoDistrito":11,"Distrito":"Lisboa","Latitude":"38.731658","Longitude":"-9.172087"},{"ID":4,"CodigoPostal":"1070-161","Morada":"Rua José da Silva Pais","Localidade":"LISBOA","Freguesia":"Campolide","Concelho":"Lisboa","CodigoDistrito":11,"Distrito":"Lisboa","Latitude":"38.731658","Longitude":"-9.172087"},{"ID":5,"CodigoPostal":"1070-161","Morada":"Rua José da Silva Pais","Localidade":"LISBOA","Freguesia":"Campolide","Concelho":"Lisboa","CodigoDistrito":11,"Distrito":"Lisboa","Latitude":"38.731658","Longitude":"-9.172087"},{"ID":6,"CodigoPostal":"1070-161","Morada":"Rua José da Silva Pais","Localidade":"LISBOA","Freguesia":"Campolide","Concelho":"Lisboa","CodigoDistrito":11,"Distrito":"Lisboa","Latitude":"38.731658","Longitude":"-9.172087"},{"ID":7,"CodigoPostal":"1070-161","Morada":"Rua José da Silva Pais","Localidade":"LISBOA","Freguesia":"Campolide","Concelho":"Lisboa","CodigoDistrito":11,"Distrito":"Lisboa","Latitude":"38.731658","Longitude":"-9.172087"},{"ID":8,"CodigoPostal":"1070-161","Morada":"Rua José da Silva Pais","Localidade":"LISBOA","Freguesia":"Campolide","Concelho":"Lisboa","CodigoDistrito":11,"Distrito":"Lisboa","Latitude":"38.731658","Longitude":"-9.172087"}]