[{"ID":1,"CodigoPostal":"1990-427","Morada":"Rotunda das Oliveiras","Localidade":"MOSCAVIDE","Freguesia":"Moscavide","Concelho":"Loures","CodigoDistrito":11,"Distrito":"Lisboa","Latitude":"38.781571","Longitude":"-9.096816"},{"ID":2,"CodigoPostal":"1990-427","Morada":"Rotunda das Oliveiras","Localidade":"MOSCAVIDE","Freguesia":"Moscavide","Concelho":"Loures","CodigoDistrito":11,"Distrito":"Lisboa","Latitude":"38.781571","Longitude":"-9.096816"},{"ID":3,"CodigoPostal":"1990-427","Morada":"Rotunda das Oliveiras","Localidade":"MOSCAVIDE","Freguesia":"Moscavide","Concelho":"Loures","CodigoDistrito":11,"Distrito":"Lisboa","Latitude":"38.781571","Longitude":"-9.096816"},{"ID":4,"CodigoPostal":"1990-427","Morada":"Rotunda das Oliveiras","Localidade":"MOSCAVIDE","Freguesia":"Moscavide","Concelho":"Loures","CodigoDistrito":11,"Distrito":"Lisboa","Latitude":"38.781571","Longitude":"-9.096816"},{"ID":5,"CodigoPostal":"1990-427","Morada":"Rotunda das Oliveiras","Localidade":"LISBOA","Freguesia":"Moscavide","Concelho":"Loures","CodigoDistrito":11,"Distrito":"Lisboa","Latitude":"38.781571","Longitude":"-9.096816"}]