[{"ID":1,"CodigoPostal":"2380-530","Morada":"Rua do Bairro Novo","Localidade":"MALHOU","Freguesia":"Malhou","Concelho":"Alcanena","CodigoDistrito":0,"Distrito":"Santarém","Latitude":"39.424514","Longitude":"-8.686419"},{"ID":2,"CodigoPostal":"2380-530","Morada":"Largo do Navio","Localidade":"MALHOU","Freguesia":"Malhou","Concelho":"Alcanena","CodigoDistrito":0,"Distrito":"Santarém","Latitude":"39.424514","Longitude":"-8.686419"},{"ID":3,"CodigoPostal":"2380-530","Morada":"Travessa 9 de Abril","Localidade":"MALHOU","Freguesia":"Malhou","Concelho":"Alcanena","CodigoDistrito":0,"Distrito":"Santarém","Latitude":"39.424514","Longitude":"-8.686419"}]