[{"ID":1,"CodigoPostal":"2430-048","Morada":"Rua de Diu","Localidade":"MARINHA GRANDE","Freguesia":"Marinha Grande","Concelho":"Marinha Grande","CodigoDistrito":10,"Distrito":"Leiria","Latitude":"39.740644","Longitude":"-8.921410"},{"ID":2,"CodigoPostal":"2430-048","Morada":"Travessa de Diu","Localidade":"MARINHA GRANDE","Freguesia":"Marinha Grande","Concelho":"Marinha Grande","CodigoDistrito":10,"Distrito":"Leiria","Latitude":"39.740644","Longitude":"-8.921410"},{"ID":3,"CodigoPostal":"2430-048","Morada":"Benta","Localidade":"MARINHA GRANDE","Freguesia":"Marinha Grande","Concelho":"Marinha Grande","CodigoDistrito":10,"Distrito":"Leiria","Latitude":"39.740644","Longitude":"-8.921410"},{"ID":4,"CodigoPostal":"2430-048","Morada":"Travessa de Diu","Localidade":"MARINHA GRANDE","Freguesia":"Marinha Grande","Concelho":"Marinha Grande","CodigoDistrito":10,"Distrito":"Leiria","Latitude":"39.740644","Longitude":"-8.921410"}]