[{"ID":1,"CodigoPostal":"2600-203","Morada":"Parque Urbano de Vila Franca de Xira","Localidade":"VILA FRANCA DE XIRA","Freguesia":"Vila Franca de Xira","Concelho":"Vila Franca de Xira","CodigoDistrito":11,"Distrito":"Lisboa","Latitude":"38.954899","Longitude":"-8.991481"},{"ID":2,"CodigoPostal":"2600-203","Morada":"Estrada Nacional 10","Localidade":"VILA FRANCA DE XIRA","Freguesia":"Alverca do Ribatejo","Concelho":"Vila Franca de Xira","CodigoDistrito":11,"Distrito":"Lisboa","Latitude":"38.954899","Longitude":"-8.991481"}]