[{"ID":1,"CodigoPostal":"2655-461","Morada":"Praceta das Amoras","Localidade":"ERICEIRA","Freguesia":"Ericeira","Concelho":"Mafra","CodigoDistrito":11,"Distrito":"Lisboa","Latitude":"38.956722","Longitude":"-9.404326"},{"ID":2,"CodigoPostal":"2655-461","Morada":"Praceta dos Pinheiros","Localidade":"ERICEIRA","Freguesia":"Ericeira","Concelho":"Mafra","CodigoDistrito":11,"Distrito":"Lisboa","Latitude":"38.956722","Longitude":"-9.404326"},{"ID":3,"CodigoPostal":"2655-461","Morada":"Caminho Vale Carneiro","Localidade":"ERICEIRA","Freguesia":"Ericeira","Concelho":"Mafra","CodigoDistrito":11,"Distrito":"Lisboa","Latitude":"38.957128","Longitude":"-9.403238"},{"ID":4,"CodigoPostal":"2655-461","Morada":"Rua Vale Carneiro","Localidade":"ERICEIRA","Freguesia":"Ericeira","Concelho":"Mafra","CodigoDistrito":11,"Distrito":"Lisboa","Latitude":"38.958288","Longitude":"-9.407700"}]