[{"ID":1,"CodigoPostal":"2665-616","Morada":"Travessa Mira Montes","Localidade":"VENDA DO PINHEIRO","Freguesia":"Venda do Pinheiro","Concelho":"Mafra","CodigoDistrito":11,"Distrito":"Lisboa","Latitude":"38.931744","Longitude":"-9.233896"},{"ID":2,"CodigoPostal":"2665-616","Morada":"Rua São José","Localidade":"VENDA DO PINHEIRO","Freguesia":"Venda do Pinheiro","Concelho":"Mafra","CodigoDistrito":11,"Distrito":"Lisboa","Latitude":"38.932456","Longitude":"-9.233849"},{"ID":3,"CodigoPostal":"2665-616","Morada":"Travessa São José","Localidade":"VENDA DO PINHEIRO","Freguesia":"Venda do Pinheiro","Concelho":"Mafra","CodigoDistrito":11,"Distrito":"Lisboa","Latitude":"38.932669","Longitude":"-9.233360"}]