[{"ID":1,"CodigoPostal":"2755-008","Morada":"Avenida de Sintra","Localidade":"ALCABIDECHE","Freguesia":"Alcabideche","Concelho":"Cascais","CodigoDistrito":11,"Distrito":"Lisboa","Latitude":"38.719004","Longitude":"-9.416980"},{"ID":2,"CodigoPostal":"2755-008","Morada":"Avenida de Sintra","Localidade":"ALCABIDECHE","Freguesia":"Alcabideche","Concelho":"Cascais","CodigoDistrito":11,"Distrito":"Lisboa","Latitude":"38.719004","Longitude":"-9.416980"},{"ID":3,"CodigoPostal":"2755-008","Morada":"Avenida de Sintra","Localidade":"ALCABIDECHE","Freguesia":"Alcabideche","Concelho":"Cascais","CodigoDistrito":11,"Distrito":"Lisboa","Latitude":"38.719004","Longitude":"-9.416980"},{"ID":4,"CodigoPostal":"2755-008","Morada":"Avenida de Sintra","Localidade":"ALCABIDECHE","Freguesia":"Alcabideche","Concelho":"Cascais","CodigoDistrito":11,"Distrito":"Lisboa","Latitude":"38.719004","Longitude":"-9.416980"},{"ID":5,"CodigoPostal":"2755-008","Morada":"Avenida de Sintra","Localidade":"ALCABIDECHE","Freguesia":"Alcabideche","Concelho":"Cascais","CodigoDistrito":11,"Distrito":"Lisboa","Latitude":"38.719004","Longitude":"-9.416980"},{"ID":6,"CodigoPostal":"2755-008","Morada":"Avenida de Sintra","Localidade":"ALCABIDECHE","Freguesia":"Alcabideche","Concelho":"Cascais","CodigoDistrito":11,"Distrito":"Lisboa","Latitude":"38.719004","Longitude":"-9.416980"},{"ID":7,"CodigoPostal":"2755-008","Morada":"Avenida de Sintra","Localidade":"ALCABIDECHE","Freguesia":"Alcabideche","Concelho":"Cascais","CodigoDistrito":11,"Distrito":"Lisboa","Latitude":"38.719004","Longitude":"-9.416980"},{"ID":8,"CodigoPostal":"2755-008","Morada":"Avenida de Sintra","Localidade":"ALCABIDECHE","Freguesia":"Alcabideche","Concelho":"Cascais","CodigoDistrito":11,"Distrito":"Lisboa","Latitude":"38.719004","Longitude":"-9.416980"},{"ID":9,"CodigoPostal":"2755-008","Morada":"Avenida de Sintra","Localidade":"ALCABIDECHE","Freguesia":"Alcabideche","Concelho":"Cascais","CodigoDistrito":11,"Distrito":"Lisboa","Latitude":"38.719004","Longitude":"-9.416980"}]