[{"ID":1,"CodigoPostal":"2785-219","Morada":"Rua Joaquim Farinha Martins","Localidade":"SÃO DOMINGOS DE RANA","Freguesia":"São Domingos de Rana","Concelho":"Cascais","CodigoDistrito":11,"Distrito":"Lisboa","Latitude":"38.740771","Longitude":"-9.339692"},{"ID":2,"CodigoPostal":"2785-219","Morada":"Rua Mato da Cruz","Localidade":"SÃO DOMINGOS DE RANA","Freguesia":"São Domingos de Rana","Concelho":"Cascais","CodigoDistrito":11,"Distrito":"Lisboa","Latitude":"38.702279","Longitude":"-9.338100"},{"ID":3,"CodigoPostal":"2785-219","Morada":"Rua 1º de Maio","Localidade":"SÃO DOMINGOS DE RANA","Freguesia":"São Domingos de Rana","Concelho":"Cascais","CodigoDistrito":11,"Distrito":"Lisboa","Latitude":"38.719584","Longitude":"-9.344887"},{"ID":4,"CodigoPostal":"2785-219","Morada":"Rua Dona Maria I","Localidade":"SÃO DOMINGOS DE RANA","Freguesia":"São Domingos de Rana","Concelho":"Cascais","CodigoDistrito":11,"Distrito":"Lisboa","Latitude":"38.742475","Longitude":"-9.339515"}]