[{"ID":1,"CodigoPostal":"2820-658","Morada":"Praceta do Girassol","Localidade":"CHARNECA DA CAPARICA","Freguesia":"Charneca da Caparica","Concelho":"Almada","CodigoDistrito":0,"Distrito":"Setúbal","Latitude":"38.581007","Longitude":"-9.186178"},{"ID":2,"CodigoPostal":"2820-658","Morada":"Avenida Sacadura Cabral","Localidade":"CHARNECA DA CAPARICA","Freguesia":"Charneca da Caparica","Concelho":"Almada","CodigoDistrito":0,"Distrito":"Setúbal","Latitude":"38.584056","Longitude":"-9.177107"},{"ID":3,"CodigoPostal":"2820-658","Morada":"Avenida Sacadura Cabral","Localidade":"CHARNECA DA CAPARICA","Freguesia":"Charneca da Caparica","Concelho":"Almada","CodigoDistrito":0,"Distrito":"Setúbal","Latitude":"38.584056","Longitude":"-9.177107"},{"ID":4,"CodigoPostal":"2820-658","Morada":"Avenida Sacadura Cabral","Localidade":"CHARNECA DA CAPARICA","Freguesia":"Charneca da Caparica","Concelho":"Almada","CodigoDistrito":0,"Distrito":"Setúbal","Latitude":"38.584056","Longitude":"-9.177107"},{"ID":5,"CodigoPostal":"2820-658","Morada":"Avenida Sacadura Cabral","Localidade":"CHARNECA DA CAPARICA","Freguesia":"Charneca da Caparica","Concelho":"Almada","CodigoDistrito":0,"Distrito":"Setúbal","Latitude":"38.584056","Longitude":"-9.177107"},{"ID":6,"CodigoPostal":"2820-658","Morada":"Avenida Sacadura Cabral","Localidade":"CHARNECA DA CAPARICA","Freguesia":"Charneca da Caparica","Concelho":"Almada","CodigoDistrito":0,"Distrito":"Setúbal","Latitude":"38.584056","Longitude":"-9.177107"},{"ID":7,"CodigoPostal":"2820-658","Morada":"Avenida Sacadura Cabral","Localidade":"CHARNECA DA CAPARICA","Freguesia":"Charneca da Caparica","Concelho":"Almada","CodigoDistrito":0,"Distrito":"Setúbal","Latitude":"38.584056","Longitude":"-9.177107"},{"ID":8,"CodigoPostal":"2820-658","Morada":"Avenida Sacadura Cabral","Localidade":"CHARNECA DA CAPARICA","Freguesia":"Charneca da Caparica","Concelho":"Almada","CodigoDistrito":0,"Distrito":"Setúbal","Latitude":"38.584056","Longitude":"-9.177107"},{"ID":9,"CodigoPostal":"2820-658","Morada":"Avenida Sacadura Cabral","Localidade":"CHARNECA DA CAPARICA","Freguesia":"Charneca da Caparica","Concelho":"Almada","CodigoDistrito":0,"Distrito":"Setúbal","Latitude":"38.584056","Longitude":"-9.177107"},{"ID":10,"CodigoPostal":"2820-658","Morada":"Avenida Sacadura Cabral","Localidade":"CHARNECA DA CAPARICA","Freguesia":"Charneca da Caparica","Concelho":"Almada","CodigoDistrito":0,"Distrito":"Setúbal","Latitude":"38.584056","Longitude":"-9.177107"},{"ID":11,"CodigoPostal":"2820-658","Morada":"Avenida Sacadura Cabral","Localidade":"CHARNECA DA CAPARICA","Freguesia":"Charneca da Caparica","Concelho":"Almada","CodigoDistrito":0,"Distrito":"Setúbal","Latitude":"38.584056","Longitude":"-9.177107"}]