[{"ID":1,"CodigoPostal":"3040-007","Morada":"Estrada do Almegue","Localidade":"COIMBRA","Freguesia":"Santa Clara","Concelho":"Coimbra","CodigoDistrito":6,"Distrito":"Coimbra","Latitude":"40.213743","Longitude":"-8.441709"},{"ID":2,"CodigoPostal":"3040-007","Morada":"Ladeira da Mondorel","Localidade":"COIMBRA","Freguesia":"Santa Clara","Concelho":"Coimbra","CodigoDistrito":6,"Distrito":"Coimbra","Latitude":"40.195301","Longitude":"-8.454309"},{"ID":3,"CodigoPostal":"3040-007","Morada":"Estrada do Almegue","Localidade":"COIMBRA","Freguesia":"Santa Clara","Concelho":"Coimbra","CodigoDistrito":6,"Distrito":"Coimbra","Latitude":"40.213743","Longitude":"-8.441709"}]