[{"ID":1,"CodigoPostal":"3080-624","Morada":"Rua Padre Vicente","Localidade":"FIGUEIRA DA FOZ","Freguesia":"Tavarede","Concelho":"Figueira da Foz","CodigoDistrito":6,"Distrito":"Coimbra","Latitude":"40.164343","Longitude":"-8.821113"},{"ID":2,"CodigoPostal":"3080-624","Morada":"Beco da Casa Paroquial","Localidade":"FIGUEIRA DA FOZ","Freguesia":"Tavarede","Concelho":"Figueira da Foz","CodigoDistrito":6,"Distrito":"Coimbra","Latitude":"40.164343","Longitude":"-8.821113"},{"ID":3,"CodigoPostal":"3080-624","Morada":"Beco da Vala da Azenha","Localidade":"FIGUEIRA DA FOZ","Freguesia":"Tavarede","Concelho":"Figueira da Foz","CodigoDistrito":6,"Distrito":"Coimbra","Latitude":"40.171221","Longitude":"-8.844623"},{"ID":4,"CodigoPostal":"3080-624","Morada":"Rua Padre Vicente","Localidade":"FIGUEIRA DA FOZ","Freguesia":"Tavarede","Concelho":"Figueira da Foz","CodigoDistrito":6,"Distrito":"Coimbra","Latitude":"40.169186","Longitude":"-8.845353"}]