[{"ID":1,"CodigoPostal":"3090-476","Morada":"Rua Alto da Vigia","Localidade":"MAIORCA","Freguesia":"Maiorca","Concelho":"Figueira da Foz","CodigoDistrito":6,"Distrito":"Coimbra","Latitude":"40.164881","Longitude":"-8.751541"},{"ID":2,"CodigoPostal":"3090-476","Morada":"Auto-Estrada 14","Localidade":"MAIORCA","Freguesia":"Maiorca","Concelho":"Figueira da Foz","CodigoDistrito":6,"Distrito":"Coimbra","Latitude":"40.164881","Longitude":"-8.751541"},{"ID":3,"CodigoPostal":"3090-476","Morada":"Rua da Espinheira","Localidade":"MAIORCA","Freguesia":"Maiorca","Concelho":"Figueira da Foz","CodigoDistrito":6,"Distrito":"Coimbra","Latitude":"40.159237","Longitude":"-8.755128"},{"ID":4,"CodigoPostal":"3090-476","Morada":"Beco da Bela Vista","Localidade":"MAIORCA","Freguesia":"Maiorca","Concelho":"Figueira da Foz","CodigoDistrito":6,"Distrito":"Coimbra","Latitude":"40.164881","Longitude":"-8.751541"},{"ID":5,"CodigoPostal":"3090-476","Morada":"Rua do Palácio","Localidade":"MAIORCA","Freguesia":"Maiorca","Concelho":"Figueira da Foz","CodigoDistrito":6,"Distrito":"Coimbra","Latitude":"40.166081","Longitude":"-8.756141"},{"ID":6,"CodigoPostal":"3090-476","Morada":"Largo Actor Dias","Localidade":"MAIORCA","Freguesia":"Maiorca","Concelho":"Figueira da Foz","CodigoDistrito":6,"Distrito":"Coimbra","Latitude":"40.166183","Longitude":"-8.754631"},{"ID":7,"CodigoPostal":"3090-476","Morada":"Rua do Hospital","Localidade":"MAIORCA","Freguesia":"Maiorca","Concelho":"Figueira da Foz","CodigoDistrito":6,"Distrito":"Coimbra","Latitude":"40.165780","Longitude":"-8.754758"},{"ID":8,"CodigoPostal":"3090-476","Morada":"Rua das Flores","Localidade":"MAIORCA","Freguesia":"Maiorca","Concelho":"Figueira da Foz","CodigoDistrito":6,"Distrito":"Coimbra","Latitude":"40.083394","Longitude":"-8.770909"},{"ID":9,"CodigoPostal":"3090-476","Morada":"Rua das Rosas","Localidade":"MAIORCA","Freguesia":"Maiorca","Concelho":"Figueira da Foz","CodigoDistrito":6,"Distrito":"Coimbra","Latitude":"40.056585","Longitude":"-8.762795"},{"ID":10,"CodigoPostal":"3090-476","Morada":"Largo do Paço","Localidade":"MAIORCA","Freguesia":"Maiorca","Concelho":"Figueira da Foz","CodigoDistrito":6,"Distrito":"Coimbra","Latitude":"40.096253","Longitude":"-8.815611"},{"ID":11,"CodigoPostal":"3090-476","Morada":"Largo Conselheiro Lopes Branco","Localidade":"MAIORCA","Freguesia":"Maiorca","Concelho":"Figueira da Foz","CodigoDistrito":6,"Distrito":"Coimbra","Latitude":"40.165884","Longitude":"-8.755304"},{"ID":12,"CodigoPostal":"3090-476","Morada":"Rua dos Albardeiros","Localidade":"MAIORCA","Freguesia":"Maiorca","Concelho":"Figueira da Foz","CodigoDistrito":6,"Distrito":"Coimbra","Latitude":"40.165484","Longitude":"-8.754675"},{"ID":13,"CodigoPostal":"3090-476","Morada":"Rua dos Lavradores","Localidade":"MAIORCA","Freguesia":"Maiorca","Concelho":"Figueira da Foz","CodigoDistrito":6,"Distrito":"Coimbra","Latitude":"40.165474","Longitude":"-8.754175"},{"ID":14,"CodigoPostal":"3090-476","Morada":"Rua da União Filarmónica Maiorrense","Localidade":"MAIORCA","Freguesia":"Maiorca","Concelho":"Figueira da Foz","CodigoDistrito":6,"Distrito":"Coimbra","Latitude":"40.165769","Longitude":"-8.754239"},{"ID":15,"CodigoPostal":"3090-476","Morada":"Beco da União","Localidade":"MAIORCA","Freguesia":"Maiorca","Concelho":"Figueira da Foz","CodigoDistrito":6,"Distrito":"Coimbra","Latitude":"40.165893","Longitude":"-8.754292"}]