[{"ID":1,"CodigoPostal":"3430-429","Morada":"Rua Senhora da Esperança","Localidade":"CARREGAL DO SAL","Freguesia":"Oliveira do Conde","Concelho":"Carregal do Sal","CodigoDistrito":18,"Distrito":"Viseu","Latitude":"40.457930","Longitude":"-7.995486"},{"ID":2,"CodigoPostal":"3430-429","Morada":"Rua Senhora da Conceição","Localidade":"CARREGAL DO SAL","Freguesia":"Oliveira do Conde","Concelho":"Carregal do Sal","CodigoDistrito":18,"Distrito":"Viseu","Latitude":"40.457930","Longitude":"-7.995486"},{"ID":3,"CodigoPostal":"3430-429","Morada":"Rua Fernão Gomes de Góis","Localidade":"CARREGAL DO SAL","Freguesia":"Oliveira do Conde","Concelho":"Carregal do Sal","CodigoDistrito":18,"Distrito":"Viseu","Latitude":"40.457930","Longitude":"-7.995486"},{"ID":4,"CodigoPostal":"3430-429","Morada":"Travessa Fernão Gomes de Góis","Localidade":"CARREGAL DO SAL","Freguesia":"Oliveira do Conde","Concelho":"Carregal do Sal","CodigoDistrito":18,"Distrito":"Viseu","Latitude":"40.457930","Longitude":"-7.995486"}]