[{"ID":1,"CodigoPostal":"3515-312","Morada":"Rua do Pereiro","Localidade":"VISEU","Freguesia":"Campo","Concelho":"Viseu","CodigoDistrito":18,"Distrito":"Viseu","Latitude":"40.697237","Longitude":"-7.945016"},{"ID":2,"CodigoPostal":"3515-312","Morada":"Travessa do Pereiro","Localidade":"VISEU","Freguesia":"Campo","Concelho":"Viseu","CodigoDistrito":18,"Distrito":"Viseu","Latitude":"40.697881","Longitude":"-7.944826"},{"ID":3,"CodigoPostal":"3515-312","Morada":"Rua do Soito","Localidade":"VISEU","Freguesia":"Campo","Concelho":"Viseu","CodigoDistrito":18,"Distrito":"Viseu","Latitude":"40.714669","Longitude":"-8.010711"}]