[{"ID":1,"CodigoPostal":"4400-188","Morada":"Rua Joaquim Nicolau Almeida","Localidade":"VILA NOVA DE GAIA","Freguesia":"Mafamude","Concelho":"Vila Nova de Gaia","CodigoDistrito":13,"Distrito":"Porto","Latitude":"41.121269","Longitude":"-8.604449"},{"ID":2,"CodigoPostal":"4400-188","Morada":"Rua Joaquim Nicolau Almeida","Localidade":"VILA NOVA DE GAIA","Freguesia":"Mafamude","Concelho":"Vila Nova de Gaia","CodigoDistrito":13,"Distrito":"Porto","Latitude":"41.121269","Longitude":"-8.604449"},{"ID":3,"CodigoPostal":"4400-188","Morada":"Rua Joaquim Nicolau Almeida","Localidade":"VILA NOVA DE GAIA","Freguesia":"Mafamude","Concelho":"Vila Nova de Gaia","CodigoDistrito":13,"Distrito":"Porto","Latitude":"41.121269","Longitude":"-8.604449"}]