[{"ID":1,"CodigoPostal":"4410-269","Morada":"Rua do Emigrante","Localidade":"CANELAS VNG","Freguesia":"Canelas","Concelho":"Vila Nova de Gaia","CodigoDistrito":13,"Distrito":"Porto","Latitude":"41.070177","Longitude":"-8.607105"},{"ID":2,"CodigoPostal":"4410-269","Morada":"Rua Industrial da Mina","Localidade":"CANELAS VNG","Freguesia":"Canelas","Concelho":"Vila Nova de Gaia","CodigoDistrito":13,"Distrito":"Porto","Latitude":"41.067004","Longitude":"-8.612215"},{"ID":3,"CodigoPostal":"4410-269","Morada":"Rua da Mina","Localidade":"CANELAS VNG","Freguesia":"Canelas","Concelho":"Vila Nova de Gaia","CodigoDistrito":13,"Distrito":"Porto","Latitude":"41.067442","Longitude":"-8.613788"},{"ID":4,"CodigoPostal":"4410-269","Morada":"Rua de Pinhal","Localidade":"CANELAS VNG","Freguesia":"Canelas","Concelho":"Vila Nova de Gaia","CodigoDistrito":13,"Distrito":"Porto","Latitude":"41.106241","Longitude":"-8.613091"},{"ID":5,"CodigoPostal":"4410-269","Morada":"Rua de São Tiago","Localidade":"CANELAS VNG","Freguesia":"Canelas","Concelho":"Vila Nova de Gaia","CodigoDistrito":13,"Distrito":"Porto","Latitude":"41.068636","Longitude":"-8.605217"},{"ID":6,"CodigoPostal":"4410-269","Morada":"Rua da Sub Estação","Localidade":"CANELAS VNG","Freguesia":"Canelas","Concelho":"Vila Nova de Gaia","CodigoDistrito":13,"Distrito":"Porto","Latitude":"41.081396","Longitude":"-8.593162"},{"ID":7,"CodigoPostal":"4410-269","Morada":"Travessa do Emigrante","Localidade":"CANELAS VNG","Freguesia":"Canelas","Concelho":"Vila Nova de Gaia","CodigoDistrito":13,"Distrito":"Porto","Latitude":"41.068727","Longitude":"-8.604893"},{"ID":8,"CodigoPostal":"4410-269","Morada":"Rua António Sérgio","Localidade":"CANELAS VNG","Freguesia":"Canelas","Concelho":"Vila Nova de Gaia","CodigoDistrito":13,"Distrito":"Porto","Latitude":"41.103376","Longitude":"-8.608577"},{"ID":9,"CodigoPostal":"4410-269","Morada":"Rua do Castalhão","Localidade":"CANELAS VNG","Freguesia":"Canelas","Concelho":"Vila Nova de Gaia","CodigoDistrito":13,"Distrito":"Porto","Latitude":"41.069782","Longitude":"-8.611052"}]