[{"ID":1,"CodigoPostal":"4510-698","Morada":"Rua Poeta Adriano Correia de Oliveira","Localidade":"FÂNZERES","Freguesia":"Fânzeres","Concelho":"Gondomar","CodigoDistrito":13,"Distrito":"Porto","Latitude":"41.188781","Longitude":"-8.521478"},{"ID":2,"CodigoPostal":"4510-698","Morada":"Rua Poeta Ary dos Santos","Localidade":"FÂNZERES","Freguesia":"Fânzeres","Concelho":"Gondomar","CodigoDistrito":13,"Distrito":"Porto","Latitude":"41.188938","Longitude":"-8.523437"},{"ID":3,"CodigoPostal":"4510-698","Morada":"Travessa Poeta Ary dos Santos","Localidade":"FÂNZERES","Freguesia":"Fânzeres","Concelho":"Gondomar","CodigoDistrito":13,"Distrito":"Porto","Latitude":"41.188781","Longitude":"-8.521478"}]