[{"ID":1,"CodigoPostal":"4580-306","Morada":"Rua do Ladário","Localidade":"DUAS IGREJAS PRD","Freguesia":"Duas Igrejas","Concelho":"Paredes","CodigoDistrito":13,"Distrito":"Porto","Latitude":"41.238556","Longitude":"-8.365247"},{"ID":2,"CodigoPostal":"4580-306","Morada":"Travessa do Ladário","Localidade":"DUAS IGREJAS PRD","Freguesia":"Duas Igrejas","Concelho":"Paredes","CodigoDistrito":13,"Distrito":"Porto","Latitude":"41.237775","Longitude":"-8.364495"},{"ID":3,"CodigoPostal":"4580-306","Morada":"Calçada do Ladário","Localidade":"DUAS IGREJAS PRD","Freguesia":"Duas Igrejas","Concelho":"Paredes","CodigoDistrito":13,"Distrito":"Porto","Latitude":"41.238556","Longitude":"-8.365247"},{"ID":4,"CodigoPostal":"4580-306","Morada":"Travessinha do Ladário","Localidade":"DUAS IGREJAS PRD","Freguesia":"Duas Igrejas","Concelho":"Paredes","CodigoDistrito":13,"Distrito":"Porto","Latitude":"41.238556","Longitude":"-8.365247"}]