[{"ID":1,"CodigoPostal":"4580-740","Morada":"Rua do Ouzarém","Localidade":"SOBROSA","Freguesia":"Sobrosa","Concelho":"Paredes","CodigoDistrito":13,"Distrito":"Porto","Latitude":"41.243471","Longitude":"-8.347731"},{"ID":2,"CodigoPostal":"4580-740","Morada":"Rua Nossa Senhora de Fátima","Localidade":"SOBROSA","Freguesia":"Sobrosa","Concelho":"Paredes","CodigoDistrito":13,"Distrito":"Porto","Latitude":"41.225428","Longitude":"-8.380850"},{"ID":3,"CodigoPostal":"4580-740","Morada":"Travessa do Fontenário","Localidade":"SOBROSA","Freguesia":"Sobrosa","Concelho":"Paredes","CodigoDistrito":13,"Distrito":"Porto","Latitude":"41.231367","Longitude":"-8.387594"},{"ID":4,"CodigoPostal":"4580-740","Morada":"Rua de Grifão","Localidade":"SOBROSA","Freguesia":"Sobrosa","Concelho":"Paredes","CodigoDistrito":13,"Distrito":"Porto","Latitude":"41.245295","Longitude":"-8.347492"},{"ID":5,"CodigoPostal":"4580-740","Morada":"Travessa do Ousarém","Localidade":"SOBROSA","Freguesia":"Sobrosa","Concelho":"Paredes","CodigoDistrito":13,"Distrito":"Porto","Latitude":"41.243471","Longitude":"-8.347731"},{"ID":6,"CodigoPostal":"4580-740","Morada":"Carreira do Ousarém","Localidade":"SOBROSA","Freguesia":"Sobrosa","Concelho":"Paredes","CodigoDistrito":13,"Distrito":"Porto","Latitude":"41.243471","Longitude":"-8.347731"}]