[{"ID":1,"CodigoPostal":"4615-407","Morada":"Travessa da Junqueira","Localidade":"MACIEIRA DA LIXA","Freguesia":"Macieira da Lixa","Concelho":"Felgueiras","CodigoDistrito":13,"Distrito":"Porto","Latitude":"41.354773","Longitude":"-8.158089"},{"ID":2,"CodigoPostal":"4615-407","Morada":"Rua Crestins de Cima","Localidade":"MACIEIRA DA LIXA","Freguesia":"Macieira da Lixa","Concelho":"Felgueiras","CodigoDistrito":13,"Distrito":"Porto","Latitude":"41.354773","Longitude":"-8.158089"},{"ID":3,"CodigoPostal":"4615-407","Morada":"Travessa Crestins de Cima","Localidade":"MACIEIRA DA LIXA","Freguesia":"Macieira da Lixa","Concelho":"Felgueiras","CodigoDistrito":13,"Distrito":"Porto","Latitude":"41.354773","Longitude":"-8.158089"},{"ID":4,"CodigoPostal":"4615-407","Morada":"Rua Pinheiro Manso","Localidade":"MACIEIRA DA LIXA","Freguesia":"Macieira da Lixa","Concelho":"Felgueiras","CodigoDistrito":13,"Distrito":"Porto","Latitude":"41.354773","Longitude":"-8.158089"}]