[{"ID":1,"CodigoPostal":"4710-624","Morada":"Rua da Tomada","Localidade":"CRESPOS","Freguesia":"Crespos","Concelho":"Braga","CodigoDistrito":2,"Distrito":"Braga","Latitude":"41.572155","Longitude":"-8.351119"},{"ID":2,"CodigoPostal":"4710-624","Morada":"Travessa da Tomada","Localidade":"CRESPOS","Freguesia":"Crespos","Concelho":"Braga","CodigoDistrito":2,"Distrito":"Braga","Latitude":"41.601600","Longitude":"-8.356174"},{"ID":3,"CodigoPostal":"4710-624","Morada":"Beco da Tomada","Localidade":"CRESPOS","Freguesia":"Crespos","Concelho":"Braga","CodigoDistrito":2,"Distrito":"Braga","Latitude":"41.603821","Longitude":"-8.358130"}]