[{"ID":1,"CodigoPostal":"4740-611","Morada":"Caminho da Agra","Localidade":"RIO TINTO EPS","Freguesia":"Rio Tinto","Concelho":"Esposende","CodigoDistrito":2,"Distrito":"Braga","Latitude":"41.499055","Longitude":"-8.724567"},{"ID":2,"CodigoPostal":"4740-611","Morada":"Caminho do Fundelo","Localidade":"RIO TINTO EPS","Freguesia":"Rio Tinto","Concelho":"Esposende","CodigoDistrito":2,"Distrito":"Braga","Latitude":"41.499055","Longitude":"-8.724567"},{"ID":3,"CodigoPostal":"4740-611","Morada":"Travessa António Machado Gomes","Localidade":"RIO TINTO EPS","Freguesia":"Rio Tinto","Concelho":"Esposende","CodigoDistrito":2,"Distrito":"Braga","Latitude":"41.499055","Longitude":"-8.724567"},{"ID":4,"CodigoPostal":"4740-611","Morada":"Caminho Agrícola de Talhos","Localidade":"RIO TINTO EPS","Freguesia":"Rio Tinto","Concelho":"Esposende","CodigoDistrito":2,"Distrito":"Braga","Latitude":"41.499055","Longitude":"-8.724567"},{"ID":5,"CodigoPostal":"4740-611","Morada":"Caminho Agrícola de Rajó","Localidade":"RIO TINTO EPS","Freguesia":"Rio Tinto","Concelho":"Esposende","CodigoDistrito":2,"Distrito":"Braga","Latitude":"41.499055","Longitude":"-8.724567"},{"ID":6,"CodigoPostal":"4740-611","Morada":"Caminho do Prado","Localidade":"RIO TINTO EPS","Freguesia":"Rio Tinto","Concelho":"Esposende","CodigoDistrito":2,"Distrito":"Braga","Latitude":"41.499055","Longitude":"-8.724567"},{"ID":7,"CodigoPostal":"4740-611","Morada":"Caminho do Perenhão","Localidade":"RIO TINTO EPS","Freguesia":"Rio Tinto","Concelho":"Esposende","CodigoDistrito":2,"Distrito":"Braga","Latitude":"41.499055","Longitude":"-8.724567"},{"ID":8,"CodigoPostal":"4740-611","Morada":"Caminho do Perenhão","Localidade":"RIO TINTO EPS","Freguesia":"Rio Tinto","Concelho":"Esposende","CodigoDistrito":2,"Distrito":"Braga","Latitude":"41.499055","Longitude":"-8.724567"},{"ID":9,"CodigoPostal":"4740-611","Morada":"Caminho Agrícola do Pântano","Localidade":"RIO TINTO EPS","Freguesia":"Rio Tinto","Concelho":"Esposende","CodigoDistrito":2,"Distrito":"Braga","Latitude":"41.499055","Longitude":"-8.724567"},{"ID":10,"CodigoPostal":"4740-611","Morada":"Rua Padre Cândido Rodrigues Saloio","Localidade":"RIO TINTO EPS","Freguesia":"Rio Tinto","Concelho":"Esposende","CodigoDistrito":2,"Distrito":"Braga","Latitude":"41.499055","Longitude":"-8.724567"},{"ID":11,"CodigoPostal":"4740-611","Morada":"Rua do Requeixo","Localidade":"RIO TINTO EPS","Freguesia":"Rio Tinto","Concelho":"Esposende","CodigoDistrito":2,"Distrito":"Braga","Latitude":"41.499055","Longitude":"-8.724567"},{"ID":12,"CodigoPostal":"4740-611","Morada":"Rua das Rodinhas","Localidade":"RIO TINTO EPS","Freguesia":"Rio Tinto","Concelho":"Esposende","CodigoDistrito":2,"Distrito":"Braga","Latitude":"41.499269","Longitude":"-8.725271"},{"ID":13,"CodigoPostal":"4740-611","Morada":"Avenida do Parque Desportivo","Localidade":"RIO TINTO EPS","Freguesia":"Rio Tinto","Concelho":"Esposende","CodigoDistrito":2,"Distrito":"Braga","Latitude":"41.495672","Longitude":"-8.720158"},{"ID":14,"CodigoPostal":"4740-611","Morada":"Rua Manuel Faria Silva","Localidade":"RIO TINTO EPS","Freguesia":"Rio Tinto","Concelho":"Esposende","CodigoDistrito":2,"Distrito":"Braga","Latitude":"41.493824","Longitude":"-8.717897"},{"ID":15,"CodigoPostal":"4740-611","Morada":"Rua da Coturela","Localidade":"RIO TINTO EPS","Freguesia":"Rio Tinto","Concelho":"Esposende","CodigoDistrito":2,"Distrito":"Braga","Latitude":"41.497310","Longitude":"-8.718165"}]