[{"ID":1,"CodigoPostal":"4755-033","Morada":"Rua da Escola","Localidade":"ALVELOS","Freguesia":"Alvelos","Concelho":"Barcelos","CodigoDistrito":2,"Distrito":"Braga","Latitude":"41.473880","Longitude":"-8.595708"},{"ID":2,"CodigoPostal":"4755-033","Morada":"Rua das Rosas","Localidade":"ALVELOS","Freguesia":"Alvelos","Concelho":"Barcelos","CodigoDistrito":2,"Distrito":"Braga","Latitude":"41.473880","Longitude":"-8.595708"},{"ID":3,"CodigoPostal":"4755-033","Morada":"Rua da Fonte Viva","Localidade":"ALVELOS","Freguesia":"Alvelos","Concelho":"Barcelos","CodigoDistrito":2,"Distrito":"Braga","Latitude":"41.510576","Longitude":"-8.627538"}]