[{"ID":1,"CodigoPostal":"4905-537","Morada":"Rua do Outeiro","Localidade":"PORTELA SUSÃ","Freguesia":"Portela Susã","Concelho":"Viana do Castelo","CodigoDistrito":16,"Distrito":"Viana do Castelo","Latitude":"41.645474","Longitude":"-8.748520"},{"ID":2,"CodigoPostal":"4905-537","Morada":"Rua da Pia do Mouro","Localidade":"PORTELA SUSÃ","Freguesia":"Portela Susã","Concelho":"Viana do Castelo","CodigoDistrito":16,"Distrito":"Viana do Castelo","Latitude":"41.670095","Longitude":"-8.698345"},{"ID":3,"CodigoPostal":"4905-537","Morada":"Beco de Outeiro","Localidade":"PORTELA SUSÃ","Freguesia":"Portela Susã","Concelho":"Viana do Castelo","CodigoDistrito":16,"Distrito":"Viana do Castelo","Latitude":"41.647048","Longitude":"-8.709688"},{"ID":4,"CodigoPostal":"4905-537","Morada":"Rua do Martinho","Localidade":"PORTELA SUSÃ","Freguesia":"Portela Susã","Concelho":"Viana do Castelo","CodigoDistrito":16,"Distrito":"Viana do Castelo","Latitude":"41.669989","Longitude":"-8.699302"},{"ID":5,"CodigoPostal":"4905-537","Morada":"Rua do Cruzeiro","Localidade":"PORTELA SUSÃ","Freguesia":"Portela Susã","Concelho":"Viana do Castelo","CodigoDistrito":16,"Distrito":"Viana do Castelo","Latitude":"41.711294","Longitude":"-8.687870"},{"ID":6,"CodigoPostal":"4905-537","Morada":"Rua da Escola","Localidade":"PORTELA SUSÃ","Freguesia":"Portela Susã","Concelho":"Viana do Castelo","CodigoDistrito":16,"Distrito":"Viana do Castelo","Latitude":"41.631362","Longitude":"-8.742217"},{"ID":7,"CodigoPostal":"4905-537","Morada":"Rua da Cabrita","Localidade":"PORTELA SUSÃ","Freguesia":"Portela Susã","Concelho":"Viana do Castelo","CodigoDistrito":16,"Distrito":"Viana do Castelo","Latitude":"41.665389","Longitude":"-8.705718"},{"ID":8,"CodigoPostal":"4905-537","Morada":"Rua da Corredoira","Localidade":"PORTELA SUSÃ","Freguesia":"Portela Susã","Concelho":"Viana do Castelo","CodigoDistrito":16,"Distrito":"Viana do Castelo","Latitude":"41.654660","Longitude":"-8.696619"},{"ID":9,"CodigoPostal":"4905-537","Morada":"Rua da Fontinha da Lage","Localidade":"PORTELA SUSÃ","Freguesia":"Portela Susã","Concelho":"Viana do Castelo","CodigoDistrito":16,"Distrito":"Viana do Castelo","Latitude":"41.669359","Longitude":"-8.701502"},{"ID":10,"CodigoPostal":"4905-537","Morada":"Rua da Lage de Pegas","Localidade":"PORTELA SUSÃ","Freguesia":"Portela Susã","Concelho":"Viana do Castelo","CodigoDistrito":16,"Distrito":"Viana do Castelo","Latitude":"41.667672","Longitude":"-8.700960"},{"ID":11,"CodigoPostal":"4905-537","Morada":"Estrada Nova","Localidade":"PORTELA SUSÃ","Freguesia":"Portela Susã","Concelho":"Viana do Castelo","CodigoDistrito":16,"Distrito":"Viana do Castelo","Latitude":"41.651552","Longitude":"-8.776174"},{"ID":12,"CodigoPostal":"4905-537","Morada":"Largo do Souto da Torrente","Localidade":"PORTELA SUSÃ","Freguesia":"Portela Susã","Concelho":"Viana do Castelo","CodigoDistrito":16,"Distrito":"Viana do Castelo","Latitude":"41.670606","Longitude":"-8.686418"},{"ID":13,"CodigoPostal":"4905-537","Morada":"Rua do Souto da Torrente","Localidade":"PORTELA SUSÃ","Freguesia":"Portela Susã","Concelho":"Viana do Castelo","CodigoDistrito":16,"Distrito":"Viana do Castelo","Latitude":"41.670382","Longitude":"-8.687168"},{"ID":14,"CodigoPostal":"4905-537","Morada":"Quelha do Souto da Torrente","Localidade":"PORTELA SUSÃ","Freguesia":"Portela Susã","Concelho":"Viana do Castelo","CodigoDistrito":16,"Distrito":"Viana do Castelo","Latitude":"41.670164","Longitude":"-8.687266"},{"ID":15,"CodigoPostal":"4905-537","Morada":"Rua do Fulão","Localidade":"PORTELA SUSÃ","Freguesia":"Portela Susã","Concelho":"Viana do Castelo","CodigoDistrito":16,"Distrito":"Viana do Castelo","Latitude":"41.663685","Longitude":"-8.701023"}]