[{"ID":1,"CodigoPostal":"4930-515","Morada":"São Pedro da Torre","Localidade":"SÃO PEDRO DA TORRE","Freguesia":"São Pedro da Torre","Concelho":"Valença","CodigoDistrito":16,"Distrito":"Viana do Castelo","Latitude":"41.990142","Longitude":"-8.667240"},{"ID":2,"CodigoPostal":"4930-515","Morada":"Estrada Nacional 13","Localidade":"SÃO PEDRO DA TORRE","Freguesia":"São Pedro da Torre","Concelho":"Valença","CodigoDistrito":16,"Distrito":"Viana do Castelo","Latitude":"41.990142","Longitude":"-8.667240"},{"ID":3,"CodigoPostal":"4930-515","Morada":"Rua do Chão","Localidade":"SÃO PEDRO DA TORRE","Freguesia":"São Pedro da Torre","Concelho":"Valença","CodigoDistrito":16,"Distrito":"Viana do Castelo","Latitude":"41.990142","Longitude":"-8.667240"},{"ID":4,"CodigoPostal":"4930-515","Morada":"Rua da Rebolida","Localidade":"SÃO PEDRO DA TORRE","Freguesia":"São Pedro da Torre","Concelho":"Valença","CodigoDistrito":16,"Distrito":"Viana do Castelo","Latitude":"41.990142","Longitude":"-8.667240"},{"ID":5,"CodigoPostal":"4930-515","Morada":"Beco da Rebolida","Localidade":"SÃO PEDRO DA TORRE","Freguesia":"São Pedro da Torre","Concelho":"Valença","CodigoDistrito":16,"Distrito":"Viana do Castelo","Latitude":"41.990142","Longitude":"-8.667240"}]