[{"ID":1,"CodigoPostal":"4950-298","Morada":"Estrada do Sobreiro","Localidade":"MAZEDO","Freguesia":"Mazedo","Concelho":"Monção","CodigoDistrito":16,"Distrito":"Viana do Castelo","Latitude":"42.011293","Longitude":"-8.306902"},{"ID":2,"CodigoPostal":"4950-298","Morada":"Caminho do Fundo","Localidade":"MAZEDO","Freguesia":"Mazedo","Concelho":"Monção","CodigoDistrito":16,"Distrito":"Viana do Castelo","Latitude":"42.011293","Longitude":"-8.306902"},{"ID":3,"CodigoPostal":"4950-298","Morada":"Caminho da Formiga","Localidade":"MAZEDO","Freguesia":"Mazedo","Concelho":"Monção","CodigoDistrito":16,"Distrito":"Viana do Castelo","Latitude":"42.011293","Longitude":"-8.306902"},{"ID":4,"CodigoPostal":"4950-298","Morada":"Rua da Formiga","Localidade":"MAZEDO","Freguesia":"Mazedo","Concelho":"Monção","CodigoDistrito":16,"Distrito":"Viana do Castelo","Latitude":"42.011293","Longitude":"-8.306902"},{"ID":5,"CodigoPostal":"4950-298","Morada":"Estrada da Adega","Localidade":"MAZEDO","Freguesia":"Mazedo","Concelho":"Monção","CodigoDistrito":16,"Distrito":"Viana do Castelo","Latitude":"42.011293","Longitude":"-8.306902"},{"ID":6,"CodigoPostal":"4950-298","Morada":"Caminho de Santo António","Localidade":"MAZEDO","Freguesia":"Mazedo","Concelho":"Monção","CodigoDistrito":16,"Distrito":"Viana do Castelo","Latitude":"42.011293","Longitude":"-8.306902"},{"ID":7,"CodigoPostal":"4950-298","Morada":"Rua da Estrela","Localidade":"MAZEDO","Freguesia":"Mazedo","Concelho":"Monção","CodigoDistrito":16,"Distrito":"Viana do Castelo","Latitude":"42.011293","Longitude":"-8.306902"},{"ID":8,"CodigoPostal":"4950-298","Morada":"Avenida da Gandra","Localidade":"MAZEDO","Freguesia":"Mazedo","Concelho":"Monção","CodigoDistrito":16,"Distrito":"Viana do Castelo","Latitude":"42.011293","Longitude":"-8.306902"}]