[{"ID":1,"CodigoPostal":"5050-434","Morada":"Rua do Terreiro","Localidade":"CANELAS PRG","Freguesia":"Canelas","Concelho":"Peso da Régua","CodigoDistrito":17,"Distrito":"Vila Real","Latitude":"41.182813","Longitude":"-7.691257"},{"ID":2,"CodigoPostal":"5050-434","Morada":"Rua de São Gonçalo","Localidade":"CANELAS PRG","Freguesia":"Canelas","Concelho":"Peso da Régua","CodigoDistrito":17,"Distrito":"Vila Real","Latitude":"41.182813","Longitude":"-7.691257"},{"ID":3,"CodigoPostal":"5050-434","Morada":"Largo 27 de Maio","Localidade":"CANELAS PRG","Freguesia":"Canelas","Concelho":"Peso da Régua","CodigoDistrito":17,"Distrito":"Vila Real","Latitude":"41.162813","Longitude":"-7.726257"}]