[{"ID":1,"CodigoPostal":"5100-138","Morada":"Rua Direita","Localidade":"LAMEGO","Freguesia":"Sé","Concelho":"Lamego","CodigoDistrito":18,"Distrito":"Viseu","Latitude":"41.063343","Longitude":"-7.793506"},{"ID":2,"CodigoPostal":"5100-138","Morada":"Rua Direita","Localidade":"LAMEGO","Freguesia":"Sé","Concelho":"Lamego","CodigoDistrito":18,"Distrito":"Viseu","Latitude":"41.063343","Longitude":"-7.793506"},{"ID":3,"CodigoPostal":"5100-138","Morada":"Rua Direita","Localidade":"LAMEGO","Freguesia":"Sé","Concelho":"Lamego","CodigoDistrito":18,"Distrito":"Viseu","Latitude":"41.063343","Longitude":"-7.793506"}]