[{"ID":1,"CodigoPostal":"5350-025","Morada":"Rua da Portela","Localidade":"ALFÂNDEGA DA FÉ","Freguesia":"Alfândega da Fé","Concelho":"Alfandega da Fé","CodigoDistrito":0,"Distrito":"Bragança","Latitude":"41.331190","Longitude":"-6.988875"},{"ID":2,"CodigoPostal":"5350-025","Morada":"Rua Doutor António Francisco de Meneses Cordeiro","Localidade":"ALFÂNDEGA DA FÉ","Freguesia":"Alfândega da Fé","Concelho":"Alfandega da Fé","CodigoDistrito":0,"Distrito":"Bragança","Latitude":"41.331190","Longitude":"-6.988875"},{"ID":3,"CodigoPostal":"5350-025","Morada":"Beco do Ferrador","Localidade":"ALFÂNDEGA DA FÉ","Freguesia":"Alfândega da Fé","Concelho":"Alfandega da Fé","CodigoDistrito":0,"Distrito":"Bragança","Latitude":"41.331190","Longitude":"-6.988875"},{"ID":4,"CodigoPostal":"5350-025","Morada":"Beco do Forno","Localidade":"ALFÂNDEGA DA FÉ","Freguesia":"Alfândega da Fé","Concelho":"Alfandega da Fé","CodigoDistrito":0,"Distrito":"Bragança","Latitude":"41.331190","Longitude":"-6.988875"},{"ID":5,"CodigoPostal":"5350-025","Morada":"Travessa da Portela","Localidade":"ALFÂNDEGA DA FÉ","Freguesia":"Alfândega da Fé","Concelho":"Alfandega da Fé","CodigoDistrito":0,"Distrito":"Bragança","Latitude":"41.331190","Longitude":"-6.988875"},{"ID":6,"CodigoPostal":"5350-025","Morada":"Rua da Portela","Localidade":"ALFÂNDEGA DA FÉ","Freguesia":"Alfândega da Fé","Concelho":"Alfandega da Fé","CodigoDistrito":0,"Distrito":"Bragança","Latitude":"41.331190","Longitude":"-6.988875"}]