[{"ID":1,"CodigoPostal":"5450-037","Morada":"Rua de Mariais","Localidade":"VILA POUCA DE AGUIAR","Freguesia":"Vila Pouca de Aguiar","Concelho":"Vila Pouca de Aguiar","CodigoDistrito":17,"Distrito":"Vila Real","Latitude":"41.500477","Longitude":"-7.644338"},{"ID":2,"CodigoPostal":"5450-037","Morada":"Estrada Nacional 2","Localidade":"VILA POUCA DE AGUIAR","Freguesia":"Vila Pouca de Aguiar","Concelho":"Vila Pouca de Aguiar","CodigoDistrito":17,"Distrito":"Vila Real","Latitude":"41.500477","Longitude":"-7.644338"},{"ID":3,"CodigoPostal":"5450-037","Morada":"Mariais","Localidade":"VILA POUCA DE AGUIAR","Freguesia":"Vila Pouca de Aguiar","Concelho":"Vila Pouca de Aguiar","CodigoDistrito":17,"Distrito":"Vila Real","Latitude":"41.500477","Longitude":"-7.644338"}]