[{"ID":1,"CodigoPostal":"7340-213","Morada":"Rua Jorge Sampaio","Localidade":"MOSTEIROS ARR","Freguesia":"Mosteiros","Concelho":"Arronches","CodigoDistrito":12,"Distrito":"Portalegre","Latitude":"39.189384","Longitude":"-7.285513"},{"ID":2,"CodigoPostal":"7340-213","Morada":"Rua da Casa Nova","Localidade":"MOSTEIROS ARR","Freguesia":"Mosteiros","Concelho":"Arronches","CodigoDistrito":12,"Distrito":"Portalegre","Latitude":"39.189384","Longitude":"-7.285513"},{"ID":3,"CodigoPostal":"7340-213","Morada":"Estrada Municipal 517","Localidade":"MOSTEIROS ARR","Freguesia":"Mosteiros","Concelho":"Arronches","CodigoDistrito":12,"Distrito":"Portalegre","Latitude":"39.160780","Longitude":"-7.291385"}]