[{"ID":1,"CodigoPostal":"7670-213","Morada":"Monte Curral Velho","Localidade":"OURIQUE","Freguesia":"Ourique","Concelho":"Ourique","CodigoDistrito":3,"Distrito":"Beja","Latitude":"37.654439","Longitude":"-8.223989"},{"ID":2,"CodigoPostal":"7670-213","Morada":"Cerro das Pedras","Localidade":"OURIQUE","Freguesia":"Ourique","Concelho":"Ourique","CodigoDistrito":3,"Distrito":"Beja","Latitude":"37.654439","Longitude":"-8.223989"},{"ID":3,"CodigoPostal":"7670-213","Morada":"Curral Velho","Localidade":"OURIQUE","Freguesia":"Ourique","Concelho":"Ourique","CodigoDistrito":3,"Distrito":"Beja","Latitude":"37.654439","Longitude":"-8.223989"}]