[{"ID":1,"CodigoPostal":"8000-210","Morada":"Rua Antero de Quental","Localidade":"FARO","Freguesia":"Sé","Concelho":"Faro","CodigoDistrito":8,"Distrito":"Faro","Latitude":"37.016844","Longitude":"-7.924123"},{"ID":2,"CodigoPostal":"8000-210","Morada":"Beco Antero Quental","Localidade":"FARO","Freguesia":"Sé","Concelho":"Faro","CodigoDistrito":8,"Distrito":"Faro","Latitude":"37.016844","Longitude":"-7.924123"},{"ID":3,"CodigoPostal":"8000-210","Morada":"Praceta Azinheira Rebelo","Localidade":"FARO","Freguesia":"Sé","Concelho":"Faro","CodigoDistrito":8,"Distrito":"Faro","Latitude":"37.016844","Longitude":"-7.924123"}]