[{"ID":1,"CodigoPostal":"9325-373","Morada":"Caminho Luís Liberato Sousa","Localidade":"ESTREITO CÂMARA DE LOBOS","Freguesia":"Estreito Câmara de Lobos","Concelho":"Câmara de Lobos","CodigoDistrito":20,"Distrito":"Madeira","Latitude":"","Longitude":"<i>Desconhecido</i>"},{"ID":2,"CodigoPostal":"9325-373","Morada":"Entrada Nº 1 da Travessa da Furneira","Localidade":"ESTREITO CÂMARA DE LOBOS","Freguesia":"Estreito Câmara de Lobos","Concelho":"Câmara de Lobos","CodigoDistrito":20,"Distrito":"Madeira","Latitude":"","Longitude":"<i>Desconhecido</i>"},{"ID":3,"CodigoPostal":"9325-373","Morada":"Travessa da Furneira","Localidade":"ESTREITO CÂMARA DE LOBOS","Freguesia":"Estreito Câmara de Lobos","Concelho":"Câmara de Lobos","CodigoDistrito":20,"Distrito":"Madeira","Latitude":"","Longitude":"<i>Desconhecido</i>"}]