[{"ID":1,"CodigoPostal":"9500-555","Morada":"Rua da Caridade","Localidade":"PONTA DELGADA","Freguesia":"Feteiras","Concelho":"Ponta Delgada","CodigoDistrito":"42","Distrito":"Ilha de São Miguel","Latitude":"38.729982","Longitude":"-9.172537"},{"ID":2,"CodigoPostal":"9500-555","Morada":"Rua da Esperança","Localidade":"PONTA DELGADA","Freguesia":"Feteiras","Concelho":"Ponta Delgada","CodigoDistrito":"42","Distrito":"Ilha de São Miguel","Latitude":"38.729982","Longitude":"-9.172537"},{"ID":3,"CodigoPostal":"9500-555","Morada":"Rua da Fé","Localidade":"PONTA DELGADA","Freguesia":"Feteiras","Concelho":"Ponta Delgada","CodigoDistrito":"42","Distrito":"Ilha de São Miguel","Latitude":"38.729982","Longitude":"-9.172537"},{"ID":4,"CodigoPostal":"9500-555","Morada":"Rua do Cemitério","Localidade":"PONTA DELGADA","Freguesia":"Feteiras","Concelho":"Ponta Delgada","CodigoDistrito":"42","Distrito":"Ilha de São Miguel","Latitude":"38.729982","Longitude":"-9.172537"},{"ID":5,"CodigoPostal":"9500-555","Morada":"Rua dos 24","Localidade":"PONTA DELGADA","Freguesia":"Feteiras","Concelho":"Ponta Delgada","CodigoDistrito":"42","Distrito":"Ilha de São Miguel","Latitude":"38.729982","Longitude":"-9.172537"}]